subtitle_sync/constants.py
subtitle_sync/formatText.py
subtitle_sync/markScriptWithRareWordsTimestamp.py
subtitle_sync/similarity.py
subtitle_sync/sync.py
subtitle_sync/utils/extractLemmas.py
subtitle_sync/utils/fillTimetamps.py
subtitle_sync/utils/furtherSyncScript.py
subtitle_sync/utils/getMatchingDistinctWords/getMaxSimilarity.py
subtitle_sync/utils/getMatchingDistinctWords/getSimilarity.py
subtitle_sync/utils/getMatchingDistinctWords/index.py
subtitle_sync/utils/getMatchingDistinctWords/searchAlgorithms/expansionSearch.py
subtitle_sync/utils/getMatchingDistinctWords/searchAlgorithms/logSearch.py
subtitle_sync/utils/getUniqueWords.py
subtitle_sync/utils/helper.py
subtitle_sync/utils/minify.py
subtitle_sync/utils/nlpSetup.py
subtitle_sync/utils/removeTimestampOutlierFromScenes.py
subtitle_sync/utils/sortScenes.py
subtitle_sync/utils/tagTimestampToScript.py
subtitle_sync/utils/traverseDialogue.py
subtitle_sync-0.2.8.dist-info/WHEEL
subtitle_sync-0.2.8.dist-info/METADATA
subtitle_sync-0.2.8.dist-info/RECORD
