Metadata-Version: 2.1
Name: subtitle-sync
Version: 0.2.8
Summary: 
Author: VVNoodle
Author-email: brickkace@gmail.com
Requires-Python: >=3.7,<4.0
Classifier: Programming Language :: Python :: 3
Classifier: Programming Language :: Python :: 3.7
Classifier: Programming Language :: Python :: 3.8
Requires-Dist: Scrapy (>=2.0.1,<3.0.0)
Requires-Dist: autopep8 (>=1.5.3,<2.0.0)
Requires-Dist: black (>=19.10b0,<20.0)
Requires-Dist: flake8 (>=3.8.3,<4.0.0)
Requires-Dist: matplotlib (>=3.2.2,<4.0.0)
Requires-Dist: num2words (>=0.5.10,<0.6.0)
Requires-Dist: numpy (>=1.19.0,<2.0.0)
Requires-Dist: pep8 (>=1.7.1,<2.0.0)
Requires-Dist: pylint (>=2.5.3,<3.0.0)
Requires-Dist: pysbd (>=0.2.3,<0.3.0)
Requires-Dist: rope (>=0.17.0,<0.18.0)
Requires-Dist: spacy (>=2.2.4,<3.0.0)
Requires-Dist: srt (>=3.0.0,<4.0.0)
Requires-Dist: strsimpy (>=0.1.7,<0.2.0)
Requires-Dist: subliminal (>=2.0.5,<3.0.0)
Requires-Dist: tensorflow (>=2.2.0,<3.0.0)
Requires-Dist: tensorflow-gpu (>=2.2.0,<3.0.0)
Requires-Dist: tensorflow_hub (>=0.8.0,<0.9.0)
Requires-Dist: unidecode (>=1.1.1,<2.0.0)
